cryptlex/__init__.py
cryptlex/lexactivator/__init__.py
cryptlex/lexactivator/lexactivator.py
cryptlex/lexactivator/lexactivator_exception.py
cryptlex/lexactivator/lexactivator_native.py
cryptlex/lexactivator/lexrelease.py
cryptlex/lexactivator/lexstatus_codes.py
cryptlex/lexactivator/libs/linux/gcc/arm64/libLexActivator.so
cryptlex/lexactivator/libs/linux/gcc/armhf/libLexActivator.so
cryptlex/lexactivator/libs/linux/gcc/x86/libLexActivator.so
cryptlex/lexactivator/libs/linux/gcc/x86_64/libLexActivator.so
cryptlex/lexactivator/libs/linux/musl/x86_64/libLexActivator.so
cryptlex/lexactivator/libs/macos/arm64/libLexActivator.dylib
cryptlex/lexactivator/libs/macos/x86_64/libLexActivator.dylib
cryptlex/lexactivator/libs/win32/arm64/LexActivator.dll
cryptlex/lexactivator/libs/win32/x86/LexActivator.dll
cryptlex/lexactivator/libs/win32/x86_64/LexActivator.dll
cryptlex_lexactivator-3.35.1.dist-info/licenses/LICENSE.txt
cryptlex_lexactivator-3.35.1.dist-info/METADATA
cryptlex_lexactivator-3.35.1.dist-info/WHEEL
cryptlex_lexactivator-3.35.1.dist-info/top_level.txt
cryptlex_lexactivator-3.35.1.dist-info/RECORD
