Metadata-Version: 2.4
Name: cryptlex.lexactivator
Version: 3.35.1
Summary: LexActivator API wrapper for Python
Home-page: https://github.com/cryptlex/lexactivator-python
Author: Cryptlex, LLC
Author-email: support@cryptlex.com
Keywords: cryptlex lexactivator licensing
Classifier: Programming Language :: Python :: 2
Classifier: Programming Language :: Python :: 3
Classifier: License :: OSI Approved :: MIT License
Classifier: Intended Audience :: Developers
Classifier: Operating System :: OS Independent
License-File: LICENSE.txt
Dynamic: author
Dynamic: author-email
Dynamic: classifier
Dynamic: description
Dynamic: description-content-type
Dynamic: home-page
Dynamic: keywords
Dynamic: license-file
Dynamic: summary
